charmongerai/__init__.py
charmongerai/charmongerai.py
charmongerai/cli.py
charmongerai/config.py
charmongerai/context.py
charmongerai/model.py
charmongerai/retriever.py
charmongerai/settings.py
charmongerai/util.py
charmongerai/discord/__init__.py
charmongerai/discord/client.py
charmongerai/simulation/__init__.py
charmongerai/simulation/agent.py
charmongerai/simulation/simulation.py
charmongerai-0.1.0.dist-info/LICENSE.txt
charmongerai-0.1.0.dist-info/METADATA
charmongerai-0.1.0.dist-info/WHEEL
charmongerai-0.1.0.dist-info/top_level.txt
charmongerai-0.1.0.dist-info/RECORD
